EnvisionRiskRaaS/__init__.py
EnvisionRiskRaaS/core.py
envisionriskraas-1.1.8.dist-info/METADATA
envisionriskraas-1.1.8.dist-info/WHEEL
envisionriskraas-1.1.8.dist-info/licenses/LICENSE.txt
envisionriskraas-1.1.8.dist-info/RECORD
