Metadata-Version: 2.1
Name: EnvisionRiskRaaS
Version: 1.1.8
Summary: EnvisionRisk improves market risk management by providing predictive analytics for risk quantification, aiding strategic decisions and risk mitigation.
Project-URL: API webpage, https://envisionrisk.stoplight.io/docs/api-aleadomus-documentation/cjr0z7gv4x6en-harnessing-advanced-tools-for-strategic-market-risk-management
Project-URL: Homepage, https://www.envisionrisk.com/
Author-email: EnvisionRisk <support@envisionrisk.com>, Coptolon <mark@brezina.dk>
License-File: LICENSE.txt
Keywords: Market risk,Quantitative finance,Risk-as-a-service
Classifier: License :: OSI Approved :: MIT License
Classifier: Operating System :: OS Independent
Classifier: Programming Language :: Python :: 3
Requires-Python: >=3.9
Requires-Dist: pandas>=2.0.2; python_version < '3.9'
Requires-Dist: queuelib>=1.5.0; python_version < '3.9'
Requires-Dist: requests>=2.31.0; python_version < '3.9'
Requires-Dist: seaborn>=0.12; python_version < '3.9'
Requires-Dist: typing>=3.10.0.0; python_version < '3.9'
